cd_parser/__init__.py
cd_parser/regex_parser.py
cd_parser/version.py
cd_parser/xpath_parser.py
cd_parser-0.2.2.dist-info/LICENSE.md
cd_parser-0.2.2.dist-info/LICENSE.txt
cd_parser-0.2.2.dist-info/METADATA
cd_parser-0.2.2.dist-info/WHEEL
cd_parser-0.2.2.dist-info/RECORD
