Metadata-Version: 2.1
Name: cd-parser
Version: 0.2.2
Summary: Text manipulation with Xpath, Regex and clipboard actions.
License: LICENSE.MD
Author: Nick Capasso
Author-email: codedocta@gmail.com
Requires-Python: >=3.9,<4.0
Classifier: License :: Other/Proprietary License
Classifier: Programming Language :: Python :: 3
Classifier: Programming Language :: Python :: 3.9
Classifier: Programming Language :: Python :: 3.10
Classifier: Programming Language :: Python :: 3.11
Classifier: Programming Language :: Python :: 3.12
Requires-Dist: clipboard (>=0.0.4,<0.0.5)
Requires-Dist: lxml (>=5.2.2,<6.0.0)
